dkist_fits_specifications/__init__.py
dkist_fits_specifications/py.typed
dkist_fits_specifications/spec_validation_schema.yml
dkist_fits_specifications/version.py
dkist_fits_specifications/dataset_extras/__init__.py
dkist_fits_specifications/dataset_extras/dataset_extras_schema.yml
dkist_fits_specifications/dataset_extras/schemas/aggregate.yml
dkist_fits_specifications/dataset_extras/schemas/atlas.yml
dkist_fits_specifications/dataset_extras/schemas/common.yml
dkist_fits_specifications/dataset_extras/schemas/compression.yml
dkist_fits_specifications/dataset_extras/schemas/cryonirsp.yml
dkist_fits_specifications/dataset_extras/schemas/dlnirsp.yml
dkist_fits_specifications/dataset_extras/schemas/fits.yml
dkist_fits_specifications/dataset_extras/schemas/gos.yml
dkist_fits_specifications/dataset_extras/schemas/ip_task.yml
dkist_fits_specifications/dataset_extras/schemas/visp.yml
dkist_fits_specifications/dataset_extras/schemas/wavecal.yml
dkist_fits_specifications/spec122/__init__.py
dkist_fits_specifications/spec122/schemas/ao.yml
dkist_fits_specifications/spec122/schemas/camera.yml
dkist_fits_specifications/spec122/schemas/compression.yml
dkist_fits_specifications/spec122/schemas/cryonirsp.yml
dkist_fits_specifications/spec122/schemas/dkist-dkist.yml
dkist_fits_specifications/spec122/schemas/dkist-id.yml
dkist_fits_specifications/spec122/schemas/dlnirsp.yml
dkist_fits_specifications/spec122/schemas/fits.yml
dkist_fits_specifications/spec122/schemas/pac.yml
dkist_fits_specifications/spec122/schemas/telescope.yml
dkist_fits_specifications/spec122/schemas/vbi.yml
dkist_fits_specifications/spec122/schemas/visp.yml
dkist_fits_specifications/spec122/schemas/vtf.yml
dkist_fits_specifications/spec122/schemas/wfc.yml
dkist_fits_specifications/spec122/schemas/ws.yml
dkist_fits_specifications/spec214/__init__.py
dkist_fits_specifications/spec214/level0.py
dkist_fits_specifications/spec214/spec214_full_schema.yml
dkist_fits_specifications/spec214/schemas/ao.yml
dkist_fits_specifications-4.20.0.dist-info/licenses/licenses/LICENSE.rst
dkist_fits_specifications-4.20.0.dist-info/METADATA
dkist_fits_specifications-4.20.0.dist-info/WHEEL
dkist_fits_specifications-4.20.0.dist-info/top_level.txt
dkist_fits_specifications-4.20.0.dist-info/RECORD
