Metadata-Version: 2.4
Name: dkist_fits_specifications
Version: 4.20.0
Summary: Machine readable FITS specifications for DKIST data.
Home-page: https://bitbucket.org/dkistdc/dkist-fits-specifications/src/main/
Author: AURA/NSO
Author-email: stuart@cadair.com
License: BSD 3-Clause
Requires-Python: >=3.10
License-File: licenses/LICENSE.rst
Requires-Dist: yamale
Requires-Dist: pyyaml
Requires-Dist: astropy
Provides-Extra: test
Requires-Dist: pytest; extra == "test"
Requires-Dist: pytest-doctestplus; extra == "test"
Requires-Dist: pytest-cov; extra == "test"
Requires-Dist: docutils; extra == "test"
Requires-Dist: sphinx; extra == "test"
Requires-Dist: towncrier; extra == "test"
Provides-Extra: docs
Requires-Dist: sphinx; extra == "docs"
Requires-Dist: sphinx-automodapi; extra == "docs"
Requires-Dist: sphinx-autodoc-typehints; extra == "docs"
Requires-Dist: sphinx-changelog; extra == "docs"
Requires-Dist: dkist-sphinx-theme; extra == "docs"
Requires-Dist: towncrier<22.12.0; extra == "docs"
Dynamic: license-file
